{"nodes": [{"id": "portfolio_website_components_navigationgrid_tsx", "label": "NavigationGrid.tsx", "file_type": "code", "source_file": "Portfolio_website\\components\\NavigationGrid.tsx", "source_location": "L1"}, {"id": "navigationgrid_navigationgrid", "label": "NavigationGrid()", "file_type": "code", "source_file": "Portfolio_website\\components\\NavigationGrid.tsx", "source_location": "L12"}], "edges": [{"source": "portfolio_website_components_navigationgrid_tsx", "target": "react", "relation": "imports_from", "confidence": "EXTRACTED", "source_file": "Portfolio_website\\components\\NavigationGrid.tsx", "source_location": "L3", "weight": 1.0}, {"source": "portfolio_website_components_navigationgrid_tsx", "target": "lucide_react", "relation": "imports_from", "confidence": "EXTRACTED", "source_file": "Portfolio_website\\components\\NavigationGrid.tsx", "source_location": "L4", "weight": 1.0}, {"source": "portfolio_website_components_navigationgrid_tsx", "target": "data", "relation": "imports_from", "confidence": "EXTRACTED", "source_file": "Portfolio_website\\components\\NavigationGrid.tsx", "source_location": "L5", "weight": 1.0}, {"source": "portfolio_website_components_navigationgrid_tsx", "target": "navigationgrid_navigationgrid", "relation": "contains", "confidence": "EXTRACTED", "source_file": "Portfolio_website\\components\\NavigationGrid.tsx", "source_location": "L12", "weight": 1.0}]}